firmament/__init__.py
firmament/compute.py
firmament/search.py
firmament-0.1.0.dist-info/licenses/LICENSE.txt
firmament-0.1.0.dist-info/METADATA
firmament-0.1.0.dist-info/WHEEL
firmament-0.1.0.dist-info/top_level.txt
firmament-0.1.0.dist-info/RECORD
