Metadata-Version: 2.4
Name: firmament
Version: 0.1.0
Summary: Methods to perform gene signature search on scRNA-seq datasets
Home-page: https://github.com/genentech/firmament
Author: Jayaram Kancherla
Author-email: jayaram.kancherla@gmail.com
License: MIT
Project-URL: Documentation, https://github.com/genentech/firmament
Platform: any
Classifier: Development Status :: 4 - Beta
Classifier: Programming Language :: Python
Requires-Python: >=3.10
License-File: LICENSE.txt
Requires-Dist: importlib-metadata; python_version < "3.8"
Requires-Dist: pandas
Requires-Dist: numpy
Requires-Dist: scipy
Requires-Dist: requests
Requires-Dist: statsmodels
Requires-Dist: pyarrow
Requires-Dist: pegasuspy>=1.7.1
Requires-Dist: anndata
Provides-Extra: testing
Requires-Dist: setuptools; extra == "testing"
Requires-Dist: pytest; extra == "testing"
Requires-Dist: pytest-cov; extra == "testing"
Dynamic: license-file
